easytext/__init__.py
easytext/component/__init__.py
easytext/component/component.py
easytext/component/component_builtin_key.py
easytext/component/factory/__init__.py
easytext/component/factory/component_factory.py
easytext/component/register/__init__.py
easytext/component/register/component_register.py
easytext/component/register/easytext_register.py
easytext/component/register/registy.py
easytext/data/__init__.py
easytext/data/instance.py
easytext/data/instance_factory.py
easytext/data/model_collate.py
easytext/data/pretrained_vocabulary.py
easytext/data/vocabulary.py
easytext/data/pretrained_word_embedding_loader/__init__.py
easytext/data/pretrained_word_embedding_loader/general_pretrained_word_embedding_loader.py
easytext/data/pretrained_word_embedding_loader/glove_loader.py
easytext/data/pretrained_word_embedding_loader/pretrained_word_embedding_loader.py
easytext/data/pretrained_word_embedding_loader/sgns_loader.py
easytext/data/tokenizer/__init__.py
easytext/data/tokenizer/en_tokenizer.py
easytext/data/tokenizer/token.py
easytext/data/tokenizer/tokenizer.py
easytext/data/tokenizer/zh_tokenizer.py
easytext/distributed/__init__.py
easytext/distributed/distributed.py
easytext/distributed/parameter.py
easytext/distributed/synchronized.py
easytext/label_decoder/__init__.py
easytext/label_decoder/model_label_decoder.py
easytext/label_decoder/label_decoder/__init__.py
easytext/label_decoder/label_decoder/label_decoder.py
easytext/label_decoder/label_decoder/sequence_label_decoder.py
easytext/label_decoder/label_index_decoder/__init__.py
easytext/label_decoder/label_index_decoder/crf_label_index_decoder.py
easytext/label_decoder/label_index_decoder/label_index_decoder.py
easytext/label_decoder/label_index_decoder/max_label_index_decoder.py
easytext/label_decoder/label_index_decoder/sequence_max_label_index_decoder.py
easytext/loss/__init__.py
easytext/loss/loss.py
easytext/metrics/__init__.py
easytext/metrics/acc_metric.py
easytext/metrics/f1_metric.py
easytext_nlp-0.4.2.dist-info/LICENSE
easytext_nlp-0.4.2.dist-info/METADATA
easytext_nlp-0.4.2.dist-info/WHEEL
easytext_nlp-0.4.2.dist-info/top_level.txt
easytext_nlp-0.4.2.dist-info/RECORD
