Metadata-Version: 2.1
Name: easytext-nlp
Version: 0.4.2
Summary: Make it easy to train and metric NLP model.
Home-page: https://github.com/cjopengler/easytext
Author: Pan Xu
Author-email: cjopengler@163.com
License: MIT
Platform: UNKNOWN
Classifier: Development Status :: 3 - Alpha
Classifier: Intended Audience :: Developers
Classifier: Topic :: Software Development :: Build Tools
Classifier: License :: OSI Approved :: MIT License
Classifier: Programming Language :: Python :: 3.6
Classifier: Programming Language :: Python :: 3.7
Classifier: Operating System :: OS Independent
Requires-Python: >=3.6
Requires-Dist: torch (>=1.2.0)
Requires-Dist: transformers (>=3.1.0)
Requires-Dist: tqdm (>=4.32.1)
Requires-Dist: tensorboard (>=2.2.0)
